Metadata-Version: 2.1
Name: devinci-pyconfig
Version: 0.1
Summary: A Python toolkit for managing configuration properties in a Python application
Author: devinci-it
Classifier: License :: OSI Approved :: MIT License
Classifier: Programming Language :: Python :: 3
Classifier: Programming Language :: Python :: 3.7
Classifier: Programming Language :: Python :: 3.8
Classifier: Programming Language :: Python :: 3.9
Classifier: Topic :: Software Development :: Libraries :: Python Modules
Classifier: Topic :: Utilities
